richstructlog4/__init__.py
richstructlog4/logger.py
richstructlog4-1.0.1.dist-info/METADATA
richstructlog4-1.0.1.dist-info/WHEEL
richstructlog4-1.0.1.dist-info/licenses/LICENSE.txt
richstructlog4-1.0.1.dist-info/RECORD
