Metadata-Version: 2.4
Name: richstructlog4
Version: 1.0.1
Summary: Rich-formatted structured logging for Python with automatic syntax highlighting and beautiful console output.
Author-email: urasakikeisuke <urasakikeisuke@gmail.com>
License: MIT
License-File: LICENSE.txt
Requires-Python: >=3.8
Requires-Dist: rich<15.0.0,>=4.0.0
Requires-Dist: structlog<26.0.0,>24.1.0
